main.py
projectpackju4nf3l1x-0.1.0.dist-info/METADATA
projectpackju4nf3l1x-0.1.0.dist-info/WHEEL
projectpackju4nf3l1x-0.1.0.dist-info/top_level.txt
projectpackju4nf3l1x-0.1.0.dist-info/RECORD
