Metadata-Version: 2.2
Name: projectpackju4nf3l1x
Version: 0.1.0
Summary: just a pack for hello world
Requires-Python: >=3.12
